{
  "project_info": {
    "project_number": "427470019034",
    "firebase_url": "https://splendid-window-195220.firebaseio.com",
    "project_id": "splendid-window-195220",
    "storage_bucket": "splendid-window-195220.appspot.com"
  },
  "client": [
    {
      "client_info": {
        "mobilesdk_app_id": "1:427470019034:android:8caae5cbd58bcfd4",
        "android_client_info": {
          "package_name": "capstone.com.doctorfinder"
        }
      },
      "oauth_client": [
        {
          "client_id": "427470019034-9ivc3qbjrjrps0jpeelcakf9vibcq11j.apps.googleusercontent.com",
          "client_type": 1,
          "android_info": {
            "package_name": "capstone.com.doctorfinder",
            "certificate_hash": "cc0d6815dcb53d75727778cbab0785c1d58a20e8"
          }
        },
        {
          "client_id": "427470019034-jl1l03ii2nt023roc94mrp6m7fugoof5.apps.googleusercontent.com",
          "client_type": 3
        }
      ],
      "api_key": [
        {
          "current_key": "AIzaSyDEGqtfkbhY-Qw8a8gcnrgLbtar9-WtHOk"
        }
      ],
      "services": {
        "analytics_service": {
          "status": 1
        },
        "appinvite_service": {
          "status": 2,
          "other_platform_oauth_client": [
            {
              "client_id": "427470019034-jl1l03ii2nt023roc94mrp6m7fugoof5.apps.googleusercontent.com",
              "client_type": 3
            }
          ]
        },
        "ads_service": {
          "status": 2
        }
      }
    }
  ],
  "configuration_version": "1"
}